betting/__init__.py
betting/convert.py
betting-0.0.4.dist-info/METADATA
betting-0.0.4.dist-info/WHEEL
betting-0.0.4.dist-info/top_level.txt
betting-0.0.4.dist-info/RECORD
