Metadata-Version: 2.1
Name: betting
Version: 0.0.4
Summary: Utility library for converting between betting odds
Home-page: https://github.com/decisionmechanics/betting
Author: Andrew Tait
Author-email: dev@decisionmechanics.com
License: MIT
Platform: UNKNOWN
Classifier: License :: OSI Approved :: MIT License
Classifier: Development Status :: 3 - Alpha
Classifier: Programming Language :: Python :: 3.8
Classifier: Intended Audience :: Developers
Classifier: Topic :: Utilities
